languages/__init__.py
languages/fields.py
languages/languages.py
languages/regions.py
django_language_fields-1.0.1.dist-info/LICENSE
django_language_fields-1.0.1.dist-info/METADATA
django_language_fields-1.0.1.dist-info/WHEEL
django_language_fields-1.0.1.dist-info/top_level.txt
django_language_fields-1.0.1.dist-info/RECORD
