Metadata-Version: 2.1
Name: django-language-fields
Version: 1.0.1
Summary: A pluggable django app that provides a comprehensive language and region choices field
Home-page: https://gitlab.com/smm-guru/django-region-language-fields
Author: Ryan Castner, Evgeny Basmov
Author-email: ryancastner@gmail.com, coykto@gmail.com
License: MIT
Keywords: django,language,languages,region,regions,fields
Platform: OS Independent
Classifier: Development Status :: 3 - Alpha
Classifier: Framework :: Django :: 1.8
Classifier: Framework :: Django :: 1.9
Classifier: Environment :: Web Environment
Classifier: Operating System :: OS Independent
Classifier: Programming Language :: Python :: 2.7
Classifier: Programming Language :: Python :: 3.5
Classifier: Intended Audience :: Developers
Classifier: License :: OSI Approved :: MIT License
License-File: LICENSE
